aio_mongo_dm/__init__.py
aio_mongo_dm/client.py
aio_mongo_dm/collections.py
aio_mongo_dm/document.py
aio_mongo_dm/exceptions.py
aio_mongo_dm/meta_base.py
aio_mongo_dm/utils.py
aio_mongo_dm-1.1.0.dist-info/LICENSE
aio_mongo_dm-1.1.0.dist-info/METADATA
aio_mongo_dm-1.1.0.dist-info/WHEEL
aio_mongo_dm-1.1.0.dist-info/top_level.txt
aio_mongo_dm-1.1.0.dist-info/RECORD
