Metadata-Version: 2.1
Name: aio-mongo-dm
Version: 1.1.0
Summary: asynchronous lightweight ODM for MongoDB based on motor
Home-page: http://github.com/kavinbj/aioMongoDM
Author: kavinbj
Author-email: kwfelix@163.com
License: MIT
Keywords: asynchronous mongodb motor odm
Classifier: Development Status :: 5 - Production/Stable
Classifier: Framework :: AsyncIO
Classifier: License :: OSI Approved :: MIT License
Classifier: Programming Language :: Python :: 3
Classifier: Programming Language :: Python :: 3.7
Classifier: Programming Language :: Python :: 3.8
Classifier: Programming Language :: Python :: 3.9
Classifier: Topic :: Software Development
Classifier: Topic :: Software Development :: Libraries
Requires-Python: >=3.7
License-File: LICENSE
Requires-Dist: motor (>=3.0)
